Metadata-Version: 2.1
Name: DiffIntegr
Version: 0.0.0
Summary: Differentiation and Integration
Home-page: UNKNOWN
Author-email: slava.esakov@mail.ru
License: MIT
Platform: UNKNOWN
